[{
    "_id": {
      "$oid": "5e171c1a6410222ddc4e0bfe"
    },
    "title": "蔬菜类",
    "fid": "1000",
    "children": [{
      "title": "茎叶花类",
      "fidd":"1000_1",
      "children":["白菜","菜花","小白菜","娃娃菜","芥菜","茼蒿","梅菜","茴香","苦苣","春笋","木耳","萝卜苗","香芹","苜蓿","雪菜","白菜","菜花","小白菜","娃娃菜","芥菜","茼蒿","梅菜","茴香","苦苣","春笋","木耳","萝卜苗","香芹","苜蓿","雪菜","白菜","菜花","小白菜","娃娃菜","芥菜","茼蒿","梅菜","茴香","苦苣","春笋","木耳","萝卜苗","香芹","苜蓿","雪菜"]
    }, {
      "title": "根茎类",
      "fidd":"1000_2",
      "children":["土豆","胡萝卜","魔芋","牛蒡","青萝卜","菱角","野蒜","苤蓝","红薯","白萝卜","山药","土豆","胡萝卜","魔芋","牛蒡","青萝卜","菱角","野蒜","苤蓝","红薯","白萝卜","山药","土豆","胡萝卜","魔芋","牛蒡","青萝卜","菱角","野蒜","苤蓝","红薯","白萝卜","山药","土豆","胡萝卜","魔芋","牛蒡","青萝卜","菱角","野蒜","苤蓝","红薯","白萝卜","山药"]
    }, {
      "title": "瓜果类",
      "fidd":"1000_3",
      "children":["茄子","黄瓜","南瓜","葫芦","佛手瓜","辣椒","黄秋葵","青椒","冬瓜","丝瓜","红椒","彩椒"]

    }, {
      "title": "菌类",
      "fidd":"1000_4",
      "children":["香菇","平菇","茶树菇","猴头菇","蘑菇","雪莲菌","虫草花","金针菇","白蘑菇","竹笋"]

    }, {
        "title": "葱蒜类",
        "fidd":"1000_5",
        "children":["洋葱","韭黄","大蒜","葱白","韭菜","大葱","小葱","青蒜","蒜苔","蒜","蒜苗"]
      }, {
      "title": "鲜豆类",
      "fidd":"1000_6",
      "children":["豆角","绿豆芽","扁豆","刀豆","芸豆","山药豆","四季豆","黄豆芽","豌豆苗","蚕豆","荷兰豆","毛豆"]
    }]
  },
  {
    "_id": {
      "$oid": "5e171c5205e5e72ddc22fcb6"
    },
    "title": "肉类",
    "fid": "1001",
    "children":[ {
      "title": "猪肉",
      "fidd":"1001_1",
      "children":["猪小排","五花肉","猪血","猪肘","猪肺","排骨","猪排","猪肉","猪肝","猪腰","猪耳朵"]
    }, {
      "title": "牛肉",
      "fidd":"1001_2",
      "children":["牛肉","牛肚","牛筋","牛仔骨","牛肾","牛排","牛尾","牛骨","牛腩","牛鞭","肥牛"]
    },{
      "title": "羊肉",
      "fidd":"1001_3",
      "children":["羊肉","羊蝎子","羊肾","羊排","羊肝","羊血","羊腿","羊肚","羊骨"]
    },{
      "title": "鸡肉",
      "fidd":"1001_4",
      "children":["鸡翅","鸡爪","鸡心","童子鸡","柴鸡","鸡腿","鸡胗","鸡肝","乌骨鸡","鸡血","鸡肉","鸡翅根"]
    },{
      "title": "鸭肉",
      "fidd":"1001_5",
      "children":["鸭肉","鸭胗","鸭掌","鸭肝","鸭腿","鸭翅","鸭头","鸭血","鸭舌","鸭肠"]
    },{
      "title": "肉制品",
      "fidd":"1001_6",
      "children":["腊肉","咸肉","午餐肉","腊鱼","火腿","肉松","熏肉","熏鱼","香肠","培根"]
    },{
      "title": "其他肉类",
      "fidd":"1001_7",
      "children":["鹌鹑","牛蛙","驴肉","鹧鸪","乳鸽","鸽子","兔肉","鹅肉","鸽肉","火鸡","鹿肉（梅花鹿）"]
    }]
  },
  {
    "_id": {
      "$oid": "5e171c6a05e5e72ddc22fcb7"
    },
    "title": "水产",
    "fid": "1002",
    "children":[ {
      "title": "淡水鱼",
      "fidd":"1002_1",
      "children":["草鱼","鲢鱼","银鱼","鳊鱼","鮰鱼","鲤鱼","青鱼","罗非鱼","桂鱼","鲫鱼","鲶鱼"]
    }, {
      "title": "咸水鱼",
      "fidd":"1002_2",
      "children":["带鱼","鲅鱼","鳗鱼","梭鱼","沙丁鱼","石斑鱼","老板鱼","马面鱼","鲈鱼","金枪鱼","三文鱼"]
    },{
      "title": "鱼制品",
      "fidd":"1002_3",
      "children":["鱼丸","鱼籽","鱼头","鱼干","花胶"]
    },{
      "title": "蟹",
      "fidd":"1002_4",
      "children":["螃蟹","青蟹","河蟹","梭子蟹","海蟹","大闸蟹"]
    },{
      "title": "藻类",
      "fidd":"1002_5",
      "children":["海带","海肠","发菜","海藻","苔菜","紫菜","裙带菜"]
    },{
      "title": "贝",
      "fidd":"1002_6",
      "children":["鲍鱼","蛏子","干贝","贻贝","北极贝","生蚝","蛤蜊","海螺","鲜贝","青口"]
    },{
      "title": "虾",
      "fidd":"1002_7",
      "children":["虾","河虾","皮皮虾","虾仁","虾米","对虾","海虾","龙虾","虾皮","明虾","基围虾","北极虾"]
    },{
      "title": "其他水产",
      "fidd":"1002_8",
      "children":["海参","田鸡","海蜇皮","鱿鱼","甲鱼","墨鱼","海胆"]
    }]
  },
  {
    "_id": {
      "$oid": "5e171c8305e5e72ddc22fcb8"
    },
    "title": "蛋奶类",
    "fid": "1003",
    "children":[ {
      "title": "蛋类",
      "fidd":"1003_1",
      "children":["鸡蛋","咸鸭蛋","鹅蛋","鸭蛋","鸽子蛋","鹌鹑蛋","松花蛋"]
    }, {
      "title": "奶类",
      "fidd":"1003_2",
      "children":["奶酪","黄油","奶油"]
    }]
  },
  {
    "_id": {
      "$oid": "5e171c9005e5e72ddc22fcb9"
    },
    "title": "豆类",
    "fid": "1004",
    "children":[ {
      "title": "豆类",
      "fidd":"1004_1",
      "children":["红豆","黑豆","绿豆","蚕豆","黄豆","青豆","豌豆"]
    }, {
      "title": "豆制品",
      "fidd":"1004_2",
      "children":["豆腐","豆腐干","豆浆","豆渣","豆腐丝","豆腐渣","内酯豆腐","千张","豆腐皮","油豆腐","素鸡"]
    }]
  },
  {
    "_id": {
      "$oid": "5e171c9b05e5e72ddc22fcba"
    },
    "title": "水果",
    "fid": "1005",
    "children":[ {
      "title": "水果",
      "fidd":"1005_1",
      "children":["柚子","苹果","柿子","橘子","橙子","木瓜","枣","草莓","葡萄干","椰汁","百香果","桑葚","石榴"]
    }]
  },
  {
    "_id": {
      "$oid": "5e171cab05e5e72ddc22fcbb"
    },
    "title": "干果",
    "fid": "1006",
    "children":[ {
      "title": "干果",
      "fidd":"1006_1",
      "children":["花生","核桃","莲子","海底椰","开心果","蜜枣","山核桃","碧根果","腰果","芝麻","榛子","红枣干"]
    }]
  },
  {
    "_id": {
      "$oid": "5e171cb705e5e72ddc22fcbc"
    },
    "title": "五谷",
    "fid": "1007",
    "children":[ {
      "title": "五谷",
      "fidd":"1007_1",
      "children":["糯米","黑米","面粉","芝麻","麦芽","糙米","谷芽","青稞","红曲米","大米","红米","低筋面粉"]
    }]
  },
  {
    "_id": {
      "$oid": "5e171cc405e5e72ddc22fcbd"
    },
    "title": "药材",
    "fid": "1008",
    "children":[ {
      "title": "药材",
      "fidd":"1008_1",
      "children":["燕窝","何首乌","葛根","当归","芡实","茯苓","板蓝根","车前草","山楂叶","白术","甘草","荷叶","何首乌","葛根","当归","芡实","茯苓","板蓝根","车前草","山楂叶","白术"]
    }]
  },
  {
    "_id": {
      "$oid": "5e171cd105e5e72ddc22fcbe"
    },
    "title": "调剂品",
    "fid": "1009",
    "children":[ {
      "title": "调剂品",
      "fidd":"1009_1",
      "children":["味精","白糖","豆瓣酱","辣根","芥末","胡椒粉","茴香","花生油","料酒","亚麻籽油","葡萄籽油","红糖","姜","番茄酱","干辣椒","咖喱","花椒","八角","苏打粉","耗油","茶油"]
    }]
  }
]
